yai_loguru_support/__init__.py
yai_loguru_support/base.py
yai_loguru_support/monitoring.py
yai_loguru_support/unified_config.py
yai_loguru_support/utils.py
yai_loguru_support/datadog/__init__.py
yai_loguru_support/sentry/__init__.py
yai_loguru_support/sls/__init__.py
yai_loguru_support/sls/sink.py
yai_loguru_support/strategies/__init__.py
yai_loguru_support/strategies/directory_strategies.py
yai_loguru_support-0.3.7.dist-info/METADATA
yai_loguru_support-0.3.7.dist-info/WHEEL
yai_loguru_support-0.3.7.dist-info/licenses/LICENSE
yai_loguru_support-0.3.7.dist-info/RECORD
