Metadata-Version: 2.4
Name: yai-loguru-support
Version: 0.3.7
Summary: A collection of Loguru sinks for integrating with third-party cloud logging services like Aliyun SLS, Datadog, Sentry, etc.
Project-URL: Homepage, https://github.com/yai-nexus/yai-nexus-agentkit
Project-URL: Repository, https://github.com/yai-nexus/yai-nexus-agentkit
Author-email: YAI-Nexus <contact@yai-nexus.com>
License: MIT License
License-File: LICENSE
Classifier: Development Status :: 3 - Alpha
Classifier: Intended Audience :: Developers
Classifier: License :: OSI Approved :: MIT License
Classifier: Programming Language :: Python :: 3
Classifier: Programming Language :: Python :: 3.9
Classifier: Programming Language :: Python :: 3.10
Classifier: Programming Language :: Python :: 3.11
Classifier: Topic :: Software Development :: Libraries :: Python Modules
Classifier: Topic :: System :: Logging
Requires-Python: >=3.9
Requires-Dist: loguru>=0.7.0
Requires-Dist: python-dotenv>=1.0.0
Provides-Extra: all
Requires-Dist: aliyun-log-python-sdk>=0.7.8; extra == 'all'
Requires-Dist: datadog>=0.44.0; extra == 'all'
Requires-Dist: sentry-sdk>=1.0.0; extra == 'all'
Provides-Extra: datadog
Requires-Dist: datadog>=0.44.0; extra == 'datadog'
Provides-Extra: dev
Requires-Dist: black>=23.0.0; extra == 'dev'
Requires-Dist: mypy>=1.0.0; extra == 'dev'
Requires-Dist: pytest-asyncio>=0.21.0; extra == 'dev'
Requires-Dist: pytest-cov>=4.0.0; extra == 'dev'
Requires-Dist: pytest>=7.0.0; extra == 'dev'
Requires-Dist: ruff>=0.1.0; extra == 'dev'
Provides-Extra: sentry
Requires-Dist: sentry-sdk>=1.0.0; extra == 'sentry'
Provides-Extra: sls
Requires-Dist: aliyun-log-python-sdk>=0.7.8; extra == 'sls'
